odoo/addons/l10n_jp_partner_title_qweb/README.rst
odoo/addons/l10n_jp_partner_title_qweb/__init__.py
odoo/addons/l10n_jp_partner_title_qweb/__manifest__.py
odoo/addons/l10n_jp_partner_title_qweb/data/res_partner_title_data.xml
odoo/addons/l10n_jp_partner_title_qweb/i18n/ja.po
odoo/addons/l10n_jp_partner_title_qweb/models/__init__.py
odoo/addons/l10n_jp_partner_title_qweb/models/res_partner.py
odoo/addons/l10n_jp_partner_title_qweb/models/res_partner_title.py
odoo/addons/l10n_jp_partner_title_qweb/report/templates.xml
odoo/addons/l10n_jp_partner_title_qweb/static/description/icon.png
odoo/addons/l10n_jp_partner_title_qweb/static/description/pdf-image.png
odoo/addons/l10n_jp_partner_title_qweb/tests/__init__.py
odoo/addons/l10n_jp_partner_title_qweb/tests/test_l10n_jp_partner_title.py
odoo/addons/l10n_jp_partner_title_qweb/views/res_partner_title_views.xml
odoo/addons/l10n_jp_partner_title_qweb/views/res_partner_views.xml
odoo11_addon_l10n_jp_partner_title_qweb-11.0.1.0.0.dist-info/DESCRIPTION.rst
odoo11_addon_l10n_jp_partner_title_qweb-11.0.1.0.0.dist-info/METADATA
odoo11_addon_l10n_jp_partner_title_qweb-11.0.1.0.0.dist-info/RECORD
odoo11_addon_l10n_jp_partner_title_qweb-11.0.1.0.0.dist-info/WHEEL
odoo11_addon_l10n_jp_partner_title_qweb-11.0.1.0.0.dist-info/metadata.json
odoo11_addon_l10n_jp_partner_title_qweb-11.0.1.0.0.dist-info/top_level.txt
